errformer/__init__.py
errformer/apps.py
errformer/conf.py
errformer/middleware.py
errformer/handlers/__init__.py
errformer/handlers/tg.py
errformer/services/__init__.py
errformer/services/generate_message.py
errformer/services/tg_sender.py
django_errformer-0.1.1.dist-info/METADATA
django_errformer-0.1.1.dist-info/WHEEL
django_errformer-0.1.1.dist-info/top_level.txt
django_errformer-0.1.1.dist-info/RECORD
