Metadata-Version: 2.2
Name: django-errformer
Version: 0.1.1
Summary: Send errors and logs to Telegram chat.
Home-page: https://github.com/breduin/django-errformer
Author: Oleg Tarasov
Author-email: tolegu@ya.ru
Classifier: Framework :: Django
Classifier: Programming Language :: Python :: 3
Classifier: License :: OSI Approved :: MIT License
Requires-Dist: Django>=4.0
Dynamic: author
Dynamic: author-email
Dynamic: classifier
Dynamic: description
Dynamic: description-content-type
Dynamic: home-page
Dynamic: requires-dist
Dynamic: summary
